{"frames": [
{
	"filename": "walk0",
	"frame": {"x":0,"y":0,"w":100,"h":50},
	"rotated": false,
	"trimmed": false,
	"spriteSourceSize": {"x":0,"y":0,"w":100,"h":50},
	"sourceSize": {"w":100,"h":50}
},
{
	"filename": "walk1",
	"frame": {"x":100,"y":0,"w":100,"h":50},
	"rotated": false,
	"trimmed": false,
	"spriteSourceSize": {"x":0,"y":0,"w":100,"h":50},
	"sourceSize": {"w":100,"h":50}
},
{
	"filename": "atk0",
	"frame": {"x":0,"y":0,"w":100,"h":50},
	"rotated": false,
	"trimmed": false,
	"spriteSourceSize": {"x":0,"y":0,"w":100,"h":50},
	"sourceSize": {"w":100,"h":50}
},
{
	"filename": "atk1",
	"frame": {"x":100,"y":0,"w":100,"h":50},
	"rotated": false,
	"trimmed": false,
	"spriteSourceSize": {"x":0,"y":0,"w":100,"h":50},
	"sourceSize": {"w":100,"h":50}
}
],
"meta": {
	"app": "#",
	"version": "1.0",
	"image": "enemy.png",
	"format": "RGBA8888",
	"size": {"w":244,"h":108},
	"scale": "1",
	"smartupdate": "$TexturePacker:SmartUpdate:99b2f74fa157c5b63e72b0d68be078b4:1/1$"
}
}
